OtoPy/Branding.py
OtoPy/UsefulTools.py
OtoPy/__init__.py
OtoPy-1.7.0.dist-info/LICENSE
OtoPy-1.7.0.dist-info/METADATA
OtoPy-1.7.0.dist-info/WHEEL
OtoPy-1.7.0.dist-info/top_level.txt
OtoPy-1.7.0.dist-info/RECORD
